{
  "version": "10.47.0",
  "generatedAt": "2026-06-28T00:00:00.000Z",
  "characterId": "lin_fan",
  "source": "buildMindGalaxyViewSnapshot from CharacterOS blueprint (LinFan, seeded)",
  "centerX": 500,
  "centerY": 500,
  "totalNodes": 40,
  "totalEdges": 48,
  "driftNodeCount": 40,
  "_integrity": {
    "fullStateIncluded": false,
    "rawStateIncluded": false,
    "clusterPayloadIncluded": false,
    "memoryPayloadIncluded": false,
    "routinePayloadIncluded": false
  },
  "nodes": [
    {
      "id": "personality_core:lin_fan",
      "type": "personality_core",
      "label": "林凡",
      "x": 500,
      "y": 500,
      "r": 56.871333333333325,
      "fill": "#FFD700",
      "stroke": "#FF0000",
      "w": 0.5623777777777776,
      "risk": "high",
      "z": 100,
      "drift": {
        "a": 1.4678,
        "m": 0.1594
      }
    },
    {
      "id": "memory:memory_lin_fan_origin_mother_rain_night",
      "type": "memory",
      "label": "小时候母亲在雨夜离开，他等了一整晚。",
      "x": 295.14573968135414,
      "y": 679.5179316446926,
      "r": 22.4,
      "fill": "#87CEEB",
      "stroke": "#FFA500",
      "w": 0.96,
      "risk": "medium",
      "z": 50,
      "drift": {
        "a": 4.4963,
        "m": 0.876
      }
    },
    {
      "id": "memory:memory_lin_fan_origin_first_love_silence",
      "type": "memory",
      "label": "初恋突然失联，没有解释。",
      "x": 314.35573693931934,
      "y": 675.0278465019138,
      "r": 21.59,
      "fill": "#87CEEB",
      "stroke": "#FFA500",
      "w": 0.906,
      "risk": "medium",
      "z": 50,
      "drift": {
        "a": 4.7347,
        "m": 0.8436
      }
    },
    {
      "id": "memory:memory_lin_fan_origin_wang_xue_support",
      "type": "memory",
      "label": "王雪在他最痛苦的时候陪过他。",
      "x": 675.3601986333636,
      "y": 336.1661591150719,
      "r": 19.085,
      "fill": "#87CEEB",
      "stroke": "#FFA500",
      "w": 0.739,
      "risk": "medium",
      "z": 50,
      "drift": {
        "a": 5.6552,
        "m": 0.7434
      }
    },
    {
      "id": "impact_cluster:cluster_abandonment",
      "type": "impact_cluster",
      "label": "abandonment",
      "x": 300,
      "y": 650,
      "r": 59.335,
      "fill": "rgba(100,149,237,0.3)",
      "stroke": "#FF0000",
      "w": 0.981,
      "risk": "high",
      "z": 30,
      "drift": {
        "a": 5.4094,
        "m": 0.6665
      }
    },
    {
      "id": "impact_cluster:cluster_support",
      "type": "impact_cluster",
      "label": "support",
      "x": 675,
      "y": 325,
      "r": 53.406,
      "fill": "rgba(100,149,237,0.3)",
      "stroke": "#FF0000",
      "w": 0.8116,
      "risk": "high",
      "z": 30,
      "drift": {
        "a": 2.2723,
        "m": 0.5902
      }
    },
    {
      "id": "impact_particle:particle_lin_fan_origin_mother_rain_night",
      "type": "impact_particle",
      "label": "小时候母亲在雨夜离开，他等了一整晚。",
      "x": 314.80683960830953,
      "y": 669.0120286585325,
      "r": 10.68,
      "fill": "#DDA0DD",
      "stroke": "#FF0000",
      "w": 0.96,
      "risk": "high",
      "z": 50,
      "drift": {
        "a": 5.5219,
        "m": 0.876
      }
    },
    {
      "id": "impact_particle:particle_lin_fan_origin_first_love_silence",
      "type": "impact_particle",
      "label": "初恋突然失联，没有解释。",
      "x": 308.90389893876943,
      "y": 646.0208679400433,
      "r": 10.248000000000001,
      "fill": "#DDA0DD",
      "stroke": "#FF0000",
      "w": 0.906,
      "risk": "high",
      "z": 50,
      "drift": {
        "a": 5.1135,
        "m": 0.8436
      }
    },
    {
      "id": "impact_particle:particle_lin_fan_origin_wang_xue_support",
      "type": "impact_particle",
      "label": "王雪在他最痛苦的时候陪过他。",
      "x": 671.951197361795,
      "y": 310.4871191376558,
      "r": 8.911999999999999,
      "fill": "#DDA0DD",
      "stroke": "#FF0000",
      "w": 0.739,
      "risk": "high",
      "z": 50,
      "drift": {
        "a": 4.4722,
        "m": 0.7434
      }
    },
    {
      "id": "belief:belief_8dd5b45e",
      "type": "belief",
      "label": "亲密关系并不可靠。",
      "x": 723.6470700365161,
      "y": 660.0218362101925,
      "r": 16.9752,
      "fill": "#98FB98",
      "stroke": "#228B22",
      "w": 0.2764,
      "risk": "low",
      "z": 50,
      "drift": {
        "a": 4.7478,
        "m": 0.4658
      }
    },
    {
      "id": "belief:belief_edc4c346",
      "type": "belief",
      "label": "重要的人会突然离开；等待通常没有结果。",
      "x": 774.8360458877295,
      "y": 509.4946237839029,
      "r": 16.8672,
      "fill": "#98FB98",
      "stroke": "#228B22",
      "w": 0.2704,
      "risk": "low",
      "z": 50,
      "drift": {
        "a": 0.6556,
        "m": 0.4622
      }
    },
    {
      "id": "belief:belief_579d7559",
      "type": "belief",
      "label": "王雪是少数真正靠近过他的人。",
      "x": 694.7766555749135,
      "y": 694.1315390220032,
      "r": 15.4704,
      "fill": "#98FB98",
      "stroke": "#228B22",
      "w": 0.1928,
      "risk": "low",
      "z": 50,
      "drift": {
        "a": 4.2785,
        "m": 0.4157
      }
    },
    {
      "id": "need:need_security",
      "type": "need",
      "label": "安全感缺失",
      "x": 550.3183778953006,
      "y": 614.4249135721138,
      "r": 25.502000000000002,
      "fill": "#2F2F2F",
      "stroke": "#FF0000",
      "w": 0.7751,
      "risk": "high",
      "z": 50,
      "drift": {
        "a": 6.0736,
        "m": 0.5738
      }
    },
    {
      "id": "need:need_control",
      "type": "need",
      "label": "控制感缺失",
      "x": 549.9730742159288,
      "y": 614.5761399830229,
      "r": 22.878,
      "fill": "#2F2F2F",
      "stroke": "#FF0000",
      "w": 0.6439,
      "risk": "high",
      "z": 50,
      "drift": {
        "a": 5.5554,
        "m": 0.5148
      }
    },
    {
      "id": "need:need_trust",
      "type": "need",
      "label": "信任缺失",
      "x": 576.4692105686953,
      "y": 598.8810388042143,
      "r": 22.162,
      "fill": "#2F2F2F",
      "stroke": "#FF0000",
      "w": 0.6081,
      "risk": "high",
      "z": 50,
      "drift": {
        "a": 3.7614,
        "m": 0.4986
      }
    },
    {
      "id": "need:need_attachment",
      "type": "need",
      "label": "依恋确认缺失",
      "x": 554.5362531633803,
      "y": 612.4757622374692,
      "r": 18.184,
      "fill": "#2F2F2F",
      "stroke": "#FFA500",
      "w": 0.4092,
      "risk": "medium",
      "z": 50,
      "drift": {
        "a": 2.8048,
        "m": 0.3273
      }
    },
    {
      "id": "desire:desire_security",
      "type": "desire",
      "label": "想确认对方是否仍然安全、仍然在关系中。",
      "x": 546.7620767371551,
      "y": 668.6366157725789,
      "r": 17.3012,
      "fill": "#FF6347",
      "stroke": "#FF0000",
      "w": 0.7751,
      "risk": "high",
      "z": 50,
      "drift": {
        "a": 6.1134,
        "m": 0.7651
      }
    },
    {
      "id": "desire:desire_control",
      "type": "desire",
      "label": "想通过克制、询问或拉开距离重新获得控制感。",
      "x": 623.9015270904596,
      "y": 623.5856447353499,
      "r": 15.7268,
      "fill": "#FF6347",
      "stroke": "#FF0000",
      "w": 0.6439,
      "risk": "high",
      "z": 50,
      "drift": {
        "a": 3.5299,
        "m": 0.6863
      }
    },
    {
      "id": "desire:desire_trust",
      "type": "desire",
      "label": "想获得解释和一致性证据，而不是只听安慰。",
      "x": 528.1855729604913,
      "y": 672.7152960130886,
      "r": 15.2972,
      "fill": "#FF6347",
      "stroke": "#FF0000",
      "w": 0.6081,
      "risk": "high",
      "z": 50,
      "drift": {
        "a": 3.0401,
        "m": 0.6649
      }
    },
    {
      "id": "desire:desire_attachment",
      "type": "desire",
      "label": "想确认自己没有再次被抛下。",
      "x": 582.4627378656825,
      "y": 654.3531563127095,
      "r": 12.9104,
      "fill": "#FF6347",
      "stroke": "#FFA500",
      "w": 0.4092,
      "risk": "medium",
      "z": 50,
      "drift": {
        "a": 3.3534,
        "m": 0.4364
      }
    },
    {
      "id": "behavior_bias:behavior_controlled_questioning",
      "type": "behavior_bias",
      "label": "压住情绪，先追问原因。",
      "x": 570.126238319677,
      "y": 713.7926815845947,
      "r": 12.818999999999999,
      "fill": "#FFA500",
      "stroke": "#FF0000",
      "w": 0.6819,
      "risk": "high",
      "z": 50,
      "drift": {
        "a": 6.2656,
        "m": 0.3546
      }
    },
    {
      "id": "behavior_bias:behavior_cold_distance",
      "type": "behavior_bias",
      "label": "表现得克制、冷淡，避免暴露依赖。",
      "x": 491.74630600266585,
      "y": 724.8485635608962,
      "r": 12.393,
      "fill": "#FFA500",
      "stroke": "#FF0000",
      "w": 0.6393,
      "risk": "high",
      "z": 50,
      "drift": {
        "a": 4.6722,
        "m": 0.3418
      }
    },
    {
      "id": "behavior_bias:behavior_immediate_outburst",
      "type": "behavior_bias",
      "label": "立刻爆发质问。",
      "x": 480.4686577497329,
      "y": 724.1506784952991,
      "r": 8.236,
      "fill": "#FFA500",
      "stroke": "#FF8C00",
      "w": 0.2236,
      "risk": "low",
      "z": 50,
      "drift": {
        "a": 1.6564,
        "m": 0.1447
      }
    },
    {
      "id": "temporal_process:snapshot",
      "type": "temporal_process",
      "label": "Pre-tick Snapshot",
      "x": 896.3006974968512,
      "y": 653.52770812954,
      "r": 5,
      "fill": "#E0E0E0",
      "stroke": "#A0A0A0",
      "w": 0,
      "risk": "low",
      "z": 15,
      "drift": {
        "a": 6.1058,
        "m": 0.075
      }
    },
    {
      "id": "temporal_process:meta_drift",
      "type": "temporal_process",
      "label": "Meta State Drift",
      "x": 814.0787898187801,
      "y": 786.3206485497867,
      "r": 5.5,
      "fill": "#E0E0E0",
      "stroke": "#A0A0A0",
      "w": 0.1,
      "risk": "low",
      "z": 15,
      "drift": {
        "a": 3.4966,
        "m": 0.09
      }
    },
    {
      "id": "temporal_process:decay_and_recovery",
      "type": "temporal_process",
      "label": "Decay and Recovery",
      "x": 689.4388012050288,
      "y": 880.4443988259015,
      "r": 7.5,
      "fill": "#E0E0E0",
      "stroke": "#A0A0A0",
      "w": 0.5,
      "risk": "low",
      "z": 15,
      "drift": {
        "a": 0.3514,
        "m": 0.15
      }
    },
    {
      "id": "temporal_process:homeostasis",
      "type": "temporal_process",
      "label": "Homeostatic Regulation",
      "x": 539.2140527719033,
      "y": 923.1870249253896,
      "r": 7,
      "fill": "#E0E0E0",
      "stroke": "#A0A0A0",
      "w": 0.4,
      "risk": "low",
      "z": 15,
      "drift": {
        "a": 0.0473,
        "m": 0.135
      }
    },
    {
      "id": "temporal_process:recovery_trace",
      "type": "temporal_process",
      "label": "Recovery Trace",
      "x": 383.69322921936475,
      "y": 908.7758983484481,
      "r": 5,
      "fill": "#E0E0E0",
      "stroke": "#A0A0A0",
      "w": 0,
      "risk": "low",
      "z": 15,
      "drift": {
        "a": 3.4207,
        "m": 0.075
      }
    },
    {
      "id": "temporal_process:parameter_network",
      "type": "temporal_process",
      "label": "Parameter Network Propagation",
      "x": 243.88027953881607,
      "y": 839.1573215941019,
      "r": 5,
      "fill": "#E0E0E0",
      "stroke": "#A0A0A0",
      "w": 0,
      "risk": "low",
      "z": 15,
      "drift": {
        "a": 2.1387,
        "m": 0.075
      }
    },
    {
      "id": "temporal_process:baseline_drift",
      "type": "temporal_process",
      "label": "Baseline Drift Evaluation",
      "x": 138.65771731491407,
      "y": 723.7336692228763,
      "r": 5,
      "fill": "#E0E0E0",
      "stroke": "#A0A0A0",
      "w": 0,
      "risk": "low",
      "z": 15,
      "drift": {
        "a": 0.3947,
        "m": 0.075
      }
    },
    {
      "id": "temporal_process:parameter_accumulation",
      "type": "temporal_process",
      "label": "Parameter Accumulation",
      "x": 82.23643263434178,
      "y": 578.0935450720424,
      "r": 5,
      "fill": "#E0E0E0",
      "stroke": "#A0A0A0",
      "w": 0,
      "risk": "low",
      "z": 15,
      "drift": {
        "a": 2.9104,
        "m": 0.075
      }
    },
    {
      "id": "temporal_process:parameter_adjustment_draft",
      "type": "temporal_process",
      "label": "Parameter Adjustment Draft",
      "x": 82.23643263434178,
      "y": 421.9064549279577,
      "r": 5,
      "fill": "#E0E0E0",
      "stroke": "#A0A0A0",
      "w": 0,
      "risk": "low",
      "z": 15,
      "drift": {
        "a": 5.1279,
        "m": 0.075
      }
    },
    {
      "id": "temporal_process:parameter_adjustment_preview",
      "type": "temporal_process",
      "label": "Parameter Adjustment Preview",
      "x": 138.657717314914,
      "y": 276.2663307771238,
      "r": 5,
      "fill": "#E0E0E0",
      "stroke": "#A0A0A0",
      "w": 0,
      "risk": "low",
      "z": 15,
      "drift": {
        "a": 4.4521,
        "m": 0.075
      }
    },
    {
      "id": "temporal_process:parameter_adjustment_audit",
      "type": "temporal_process",
      "label": "Parameter Adjustment Audit",
      "x": 243.88027953881596,
      "y": 160.8426784058982,
      "r": 5,
      "fill": "#E0E0E0",
      "stroke": "#A0A0A0",
      "w": 0,
      "risk": "low",
      "z": 15,
      "drift": {
        "a": 5.585,
        "m": 0.075
      }
    },
    {
      "id": "temporal_process:parameter_adjustment_patch",
      "type": "temporal_process",
      "label": "Parameter Adjustment Patch",
      "x": 383.6932292193647,
      "y": 91.2241016515519,
      "r": 5,
      "fill": "#E0E0E0",
      "stroke": "#A0A0A0",
      "w": 0,
      "risk": "low",
      "z": 15,
      "drift": {
        "a": 5.5327,
        "m": 0.075
      }
    },
    {
      "id": "temporal_process:parameter_adjustment_snapshot",
      "type": "temporal_process",
      "label": "Parameter Adjustment Snapshot",
      "x": 539.2140527719032,
      "y": 76.81297507461034,
      "r": 5,
      "fill": "#E0E0E0",
      "stroke": "#A0A0A0",
      "w": 0,
      "risk": "low",
      "z": 15,
      "drift": {
        "a": 0.074,
        "m": 0.075
      }
    },
    {
      "id": "temporal_process:boredom",
      "type": "temporal_process",
      "label": "Boredom / Inspiration Update",
      "x": 689.4388012050285,
      "y": 119.5556011740984,
      "r": 5.5,
      "fill": "#E0E0E0",
      "stroke": "#A0A0A0",
      "w": 0.1,
      "risk": "low",
      "z": 15,
      "drift": {
        "a": 5.522,
        "m": 0.09
      }
    },
    {
      "id": "temporal_process:belief_evolution",
      "type": "temporal_process",
      "label": "Belief Evolution",
      "x": 814.0787898187799,
      "y": 213.67935145021295,
      "r": 5.5,
      "fill": "#E0E0E0",
      "stroke": "#A0A0A0",
      "w": 0.1,
      "risk": "low",
      "z": 15,
      "drift": {
        "a": 2.7089,
        "m": 0.09
      }
    },
    {
      "id": "temporal_process:attention_and_reflection",
      "type": "temporal_process",
      "label": "Attention and Deep Thinking Check",
      "x": 896.3006974968512,
      "y": 346.47229187045997,
      "r": 5,
      "fill": "#E0E0E0",
      "stroke": "#A0A0A0",
      "w": 0,
      "risk": "low",
      "z": 15,
      "drift": {
        "a": 1.362,
        "m": 0.075
      }
    },
    {
      "id": "temporal_process:time_perception",
      "type": "temporal_process",
      "label": "Subjective Time Perception",
      "x": 925,
      "y": 499.9999999999999,
      "r": 5,
      "fill": "#E0E0E0",
      "stroke": "#A0A0A0",
      "w": 0,
      "risk": "low",
      "z": 15,
      "drift": {
        "a": 5.6224,
        "m": 0.075
      }
    }
  ],
  "edges": [
    {
      "id": "impacts_personality:impact_particle:particle_lin_fan_origin_mother_rain_night→personality_core:lin_fan",
      "t": "impacts_personality",
      "s": "impact_particle:particle_lin_fan_origin_mother_rain_night",
      "d": "personality_core:lin_fan",
      "w": 0.96,
      "style": {
        "stroke": "#FF6347",
        "sw": 2.5,
        "op": 0.8
      },
      "dir": 1
    },
    {
      "id": "belongs_to_cluster:impact_particle:particle_lin_fan_origin_mother_rain_night→impact_cluster:cluster_abandonment",
      "t": "belongs_to_cluster",
      "s": "impact_particle:particle_lin_fan_origin_mother_rain_night",
      "d": "impact_cluster:cluster_abandonment",
      "w": 0.96,
      "style": {
        "stroke": "#4169E1",
        "sw": 2,
        "op": 0.7
      },
      "dir": 1
    },
    {
      "id": "impacts_personality:impact_particle:particle_lin_fan_origin_first_love_silence→personality_core:lin_fan",
      "t": "impacts_personality",
      "s": "impact_particle:particle_lin_fan_origin_first_love_silence",
      "d": "personality_core:lin_fan",
      "w": 0.906,
      "style": {
        "stroke": "#FF6347",
        "sw": 2.5,
        "op": 0.8
      },
      "dir": 1
    },
    {
      "id": "belongs_to_cluster:impact_particle:particle_lin_fan_origin_first_love_silence→impact_cluster:cluster_abandonment",
      "t": "belongs_to_cluster",
      "s": "impact_particle:particle_lin_fan_origin_first_love_silence",
      "d": "impact_cluster:cluster_abandonment",
      "w": 0.906,
      "style": {
        "stroke": "#4169E1",
        "sw": 2,
        "op": 0.7
      },
      "dir": 1
    },
    {
      "id": "impacts_personality:impact_particle:particle_lin_fan_origin_wang_xue_support→personality_core:lin_fan",
      "t": "impacts_personality",
      "s": "impact_particle:particle_lin_fan_origin_wang_xue_support",
      "d": "personality_core:lin_fan",
      "w": 0.739,
      "style": {
        "stroke": "#FF6347",
        "sw": 2.5,
        "op": 0.8
      },
      "dir": 1
    },
    {
      "id": "belongs_to_cluster:impact_particle:particle_lin_fan_origin_wang_xue_support→impact_cluster:cluster_support",
      "t": "belongs_to_cluster",
      "s": "impact_particle:particle_lin_fan_origin_wang_xue_support",
      "d": "impact_cluster:cluster_support",
      "w": 0.739,
      "style": {
        "stroke": "#4169E1",
        "sw": 2,
        "op": 0.7
      },
      "dir": 1
    },
    {
      "id": "pulls_personality:impact_cluster:cluster_abandonment→personality_core:lin_fan",
      "t": "pulls_personality",
      "s": "impact_cluster:cluster_abandonment",
      "d": "personality_core:lin_fan",
      "w": 0.981,
      "style": {
        "stroke": "#FF4500",
        "sw": 2.5,
        "op": 0.8
      },
      "dir": 1
    },
    {
      "id": "pulls_personality:impact_cluster:cluster_support→personality_core:lin_fan",
      "t": "pulls_personality",
      "s": "impact_cluster:cluster_support",
      "d": "personality_core:lin_fan",
      "w": 0.8116,
      "style": {
        "stroke": "#FF4500",
        "sw": 2.5,
        "op": 0.8
      },
      "dir": 1
    },
    {
      "id": "belongs_to_cluster:memory:memory_lin_fan_origin_mother_rain_night→impact_cluster:cluster_abandonment",
      "t": "belongs_to_cluster",
      "s": "memory:memory_lin_fan_origin_mother_rain_night",
      "d": "impact_cluster:cluster_abandonment",
      "w": 0.96,
      "style": {
        "stroke": "#4169E1",
        "sw": 2,
        "op": 0.7
      },
      "dir": 1
    },
    {
      "id": "belongs_to_cluster:memory:memory_lin_fan_origin_first_love_silence→impact_cluster:cluster_abandonment",
      "t": "belongs_to_cluster",
      "s": "memory:memory_lin_fan_origin_first_love_silence",
      "d": "impact_cluster:cluster_abandonment",
      "w": 0.906,
      "style": {
        "stroke": "#4169E1",
        "sw": 2,
        "op": 0.7
      },
      "dir": 1
    },
    {
      "id": "belongs_to_cluster:memory:memory_lin_fan_origin_wang_xue_support→impact_cluster:cluster_support",
      "t": "belongs_to_cluster",
      "s": "memory:memory_lin_fan_origin_wang_xue_support",
      "d": "impact_cluster:cluster_support",
      "w": 0.739,
      "style": {
        "stroke": "#4169E1",
        "sw": 2,
        "op": 0.7
      },
      "dir": 1
    },
    {
      "id": "activates_belief:memory:memory_lin_fan_origin_first_love_silence→belief:belief_8dd5b45e",
      "t": "activates_belief",
      "s": "memory:memory_lin_fan_origin_first_love_silence",
      "d": "belief:belief_8dd5b45e",
      "w": 0.2764,
      "style": {
        "stroke": "#228B22",
        "sw": 2,
        "op": 0.7
      },
      "dir": 1
    },
    {
      "id": "activates_belief:memory:memory_lin_fan_origin_mother_rain_night→belief:belief_edc4c346",
      "t": "activates_belief",
      "s": "memory:memory_lin_fan_origin_mother_rain_night",
      "d": "belief:belief_edc4c346",
      "w": 0.2704,
      "style": {
        "stroke": "#228B22",
        "sw": 2,
        "op": 0.7
      },
      "dir": 1
    },
    {
      "id": "activates_belief:memory:memory_lin_fan_origin_wang_xue_support→belief:belief_579d7559",
      "t": "activates_belief",
      "s": "memory:memory_lin_fan_origin_wang_xue_support",
      "d": "belief:belief_579d7559",
      "w": 0.1928,
      "style": {
        "stroke": "#228B22",
        "sw": 2,
        "op": 0.7
      },
      "dir": 1
    },
    {
      "id": "derived_from:need:need_security→personality_core:lin_fan",
      "t": "derived_from",
      "s": "need:need_security",
      "d": "personality_core:lin_fan",
      "w": 0.7751,
      "style": {
        "stroke": "#A0A0A0",
        "sw": 1.5,
        "op": 0.5
      },
      "dir": 0
    },
    {
      "id": "derived_from:need:need_control→personality_core:lin_fan",
      "t": "derived_from",
      "s": "need:need_control",
      "d": "personality_core:lin_fan",
      "w": 0.6439,
      "style": {
        "stroke": "#A0A0A0",
        "sw": 1.5,
        "op": 0.5
      },
      "dir": 0
    },
    {
      "id": "derived_from:need:need_trust→personality_core:lin_fan",
      "t": "derived_from",
      "s": "need:need_trust",
      "d": "personality_core:lin_fan",
      "w": 0.6081,
      "style": {
        "stroke": "#A0A0A0",
        "sw": 1.5,
        "op": 0.5
      },
      "dir": 0
    },
    {
      "id": "derived_from:need:need_attachment→personality_core:lin_fan",
      "t": "derived_from",
      "s": "need:need_attachment",
      "d": "personality_core:lin_fan",
      "w": 0.4092,
      "style": {
        "stroke": "#A0A0A0",
        "sw": 1.5,
        "op": 0.5
      },
      "dir": 0
    },
    {
      "id": "creates_need:belief:belief_8dd5b45e→need:need_security",
      "t": "creates_need",
      "s": "belief:belief_8dd5b45e",
      "d": "need:need_security",
      "w": 0.152,
      "style": {
        "stroke": "#8B0000",
        "sw": 2,
        "op": 0.6
      },
      "dir": 1
    },
    {
      "id": "creates_need:belief:belief_8dd5b45e→need:need_trust",
      "t": "creates_need",
      "s": "belief:belief_8dd5b45e",
      "d": "need:need_trust",
      "w": 0.1382,
      "style": {
        "stroke": "#8B0000",
        "sw": 2,
        "op": 0.6
      },
      "dir": 1
    },
    {
      "id": "creates_need:belief:belief_edc4c346→need:need_security",
      "t": "creates_need",
      "s": "belief:belief_edc4c346",
      "d": "need:need_security",
      "w": 0.1487,
      "style": {
        "stroke": "#8B0000",
        "sw": 2,
        "op": 0.6
      },
      "dir": 1
    },
    {
      "id": "creates_need:belief:belief_edc4c346→need:need_control",
      "t": "creates_need",
      "s": "belief:belief_edc4c346",
      "d": "need:need_control",
      "w": 0.0946,
      "style": {
        "stroke": "#8B0000",
        "sw": 2,
        "op": 0.6
      },
      "dir": 1
    },
    {
      "id": "creates_need:belief:belief_edc4c346→need:need_trust",
      "t": "creates_need",
      "s": "belief:belief_edc4c346",
      "d": "need:need_trust",
      "w": 0.1352,
      "style": {
        "stroke": "#8B0000",
        "sw": 2,
        "op": 0.6
      },
      "dir": 1
    },
    {
      "id": "creates_need:belief:belief_edc4c346→need:need_attachment",
      "t": "creates_need",
      "s": "belief:belief_edc4c346",
      "d": "need:need_attachment",
      "w": 0.1217,
      "style": {
        "stroke": "#8B0000",
        "sw": 2,
        "op": 0.6
      },
      "dir": 1
    },
    {
      "id": "creates_need:belief:belief_579d7559→need:need_attachment",
      "t": "creates_need",
      "s": "belief:belief_579d7559",
      "d": "need:need_attachment",
      "w": 0.0868,
      "style": {
        "stroke": "#8B0000",
        "sw": 2,
        "op": 0.6
      },
      "dir": 1
    },
    {
      "id": "drives_desire:need:need_security→desire:desire_security",
      "t": "drives_desire",
      "s": "need:need_security",
      "d": "desire:desire_security",
      "w": 0.7751,
      "style": {
        "stroke": "#CD5C5C",
        "sw": 2,
        "op": 0.7
      },
      "dir": 1
    },
    {
      "id": "drives_desire:need:need_control→desire:desire_control",
      "t": "drives_desire",
      "s": "need:need_control",
      "d": "desire:desire_control",
      "w": 0.6439,
      "style": {
        "stroke": "#CD5C5C",
        "sw": 2,
        "op": 0.7
      },
      "dir": 1
    },
    {
      "id": "drives_desire:need:need_trust→desire:desire_trust",
      "t": "drives_desire",
      "s": "need:need_trust",
      "d": "desire:desire_trust",
      "w": 0.6081,
      "style": {
        "stroke": "#CD5C5C",
        "sw": 2,
        "op": 0.7
      },
      "dir": 1
    },
    {
      "id": "drives_desire:need:need_attachment→desire:desire_attachment",
      "t": "drives_desire",
      "s": "need:need_attachment",
      "d": "desire:desire_attachment",
      "w": 0.4092,
      "style": {
        "stroke": "#CD5C5C",
        "sw": 2,
        "op": 0.7
      },
      "dir": 1
    },
    {
      "id": "biases_behavior:desire:desire_security→behavior_bias:behavior_controlled_questioning",
      "t": "biases_behavior",
      "s": "desire:desire_security",
      "d": "behavior_bias:behavior_controlled_questioning",
      "w": 0.6819,
      "style": {
        "stroke": "#FF8C00",
        "sw": 2,
        "op": 0.7
      },
      "dir": 1
    },
    {
      "id": "biases_behavior:desire:desire_security→behavior_bias:behavior_cold_distance",
      "t": "biases_behavior",
      "s": "desire:desire_security",
      "d": "behavior_bias:behavior_cold_distance",
      "w": 0.6393,
      "style": {
        "stroke": "#FF8C00",
        "sw": 2,
        "op": 0.7
      },
      "dir": 1
    },
    {
      "id": "biases_behavior:desire:desire_security→behavior_bias:behavior_immediate_outburst",
      "t": "biases_behavior",
      "s": "desire:desire_security",
      "d": "behavior_bias:behavior_immediate_outburst",
      "w": 0.2236,
      "style": {
        "stroke": "#FF8C00",
        "sw": 2,
        "op": 0.7
      },
      "dir": 1
    },
    {
      "id": "temporal_transition:temporal_process:snapshot→temporal_process:meta_drift",
      "t": "temporal_transition",
      "s": "temporal_process:snapshot",
      "d": "temporal_process:meta_drift",
      "w": 1,
      "style": {
        "stroke": "#B0B0B0",
        "sw": 1,
        "op": 0.4
      },
      "dir": 1
    },
    {
      "id": "temporal_transition:temporal_process:meta_drift→temporal_process:decay_and_recovery",
      "t": "temporal_transition",
      "s": "temporal_process:meta_drift",
      "d": "temporal_process:decay_and_recovery",
      "w": 1,
      "style": {
        "stroke": "#B0B0B0",
        "sw": 1,
        "op": 0.4
      },
      "dir": 1
    },
    {
      "id": "temporal_transition:temporal_process:decay_and_recovery→temporal_process:homeostasis",
      "t": "temporal_transition",
      "s": "temporal_process:decay_and_recovery",
      "d": "temporal_process:homeostasis",
      "w": 1,
      "style": {
        "stroke": "#B0B0B0",
        "sw": 1,
        "op": 0.4
      },
      "dir": 1
    },
    {
      "id": "temporal_transition:temporal_process:homeostasis→temporal_process:recovery_trace",
      "t": "temporal_transition",
      "s": "temporal_process:homeostasis",
      "d": "temporal_process:recovery_trace",
      "w": 1,
      "style": {
        "stroke": "#B0B0B0",
        "sw": 1,
        "op": 0.4
      },
      "dir": 1
    },
    {
      "id": "temporal_transition:temporal_process:recovery_trace→temporal_process:parameter_network",
      "t": "temporal_transition",
      "s": "temporal_process:recovery_trace",
      "d": "temporal_process:parameter_network",
      "w": 1,
      "style": {
        "stroke": "#B0B0B0",
        "sw": 1,
        "op": 0.4
      },
      "dir": 1
    },
    {
      "id": "temporal_transition:temporal_process:parameter_network→temporal_process:baseline_drift",
      "t": "temporal_transition",
      "s": "temporal_process:parameter_network",
      "d": "temporal_process:baseline_drift",
      "w": 1,
      "style": {
        "stroke": "#B0B0B0",
        "sw": 1,
        "op": 0.4
      },
      "dir": 1
    },
    {
      "id": "temporal_transition:temporal_process:baseline_drift→temporal_process:parameter_accumulation",
      "t": "temporal_transition",
      "s": "temporal_process:baseline_drift",
      "d": "temporal_process:parameter_accumulation",
      "w": 1,
      "style": {
        "stroke": "#B0B0B0",
        "sw": 1,
        "op": 0.4
      },
      "dir": 1
    },
    {
      "id": "temporal_transition:temporal_process:parameter_accumulation→temporal_process:parameter_adjustment_draft",
      "t": "temporal_transition",
      "s": "temporal_process:parameter_accumulation",
      "d": "temporal_process:parameter_adjustment_draft",
      "w": 1,
      "style": {
        "stroke": "#B0B0B0",
        "sw": 1,
        "op": 0.4
      },
      "dir": 1
    },
    {
      "id": "temporal_transition:temporal_process:parameter_adjustment_draft→temporal_process:parameter_adjustment_preview",
      "t": "temporal_transition",
      "s": "temporal_process:parameter_adjustment_draft",
      "d": "temporal_process:parameter_adjustment_preview",
      "w": 1,
      "style": {
        "stroke": "#B0B0B0",
        "sw": 1,
        "op": 0.4
      },
      "dir": 1
    },
    {
      "id": "temporal_transition:temporal_process:parameter_adjustment_preview→temporal_process:parameter_adjustment_audit",
      "t": "temporal_transition",
      "s": "temporal_process:parameter_adjustment_preview",
      "d": "temporal_process:parameter_adjustment_audit",
      "w": 1,
      "style": {
        "stroke": "#B0B0B0",
        "sw": 1,
        "op": 0.4
      },
      "dir": 1
    },
    {
      "id": "temporal_transition:temporal_process:parameter_adjustment_audit→temporal_process:parameter_adjustment_patch",
      "t": "temporal_transition",
      "s": "temporal_process:parameter_adjustment_audit",
      "d": "temporal_process:parameter_adjustment_patch",
      "w": 1,
      "style": {
        "stroke": "#B0B0B0",
        "sw": 1,
        "op": 0.4
      },
      "dir": 1
    },
    {
      "id": "temporal_transition:temporal_process:parameter_adjustment_patch→temporal_process:parameter_adjustment_snapshot",
      "t": "temporal_transition",
      "s": "temporal_process:parameter_adjustment_patch",
      "d": "temporal_process:parameter_adjustment_snapshot",
      "w": 1,
      "style": {
        "stroke": "#B0B0B0",
        "sw": 1,
        "op": 0.4
      },
      "dir": 1
    },
    {
      "id": "temporal_transition:temporal_process:parameter_adjustment_snapshot→temporal_process:boredom",
      "t": "temporal_transition",
      "s": "temporal_process:parameter_adjustment_snapshot",
      "d": "temporal_process:boredom",
      "w": 1,
      "style": {
        "stroke": "#B0B0B0",
        "sw": 1,
        "op": 0.4
      },
      "dir": 1
    },
    {
      "id": "temporal_transition:temporal_process:boredom→temporal_process:belief_evolution",
      "t": "temporal_transition",
      "s": "temporal_process:boredom",
      "d": "temporal_process:belief_evolution",
      "w": 1,
      "style": {
        "stroke": "#B0B0B0",
        "sw": 1,
        "op": 0.4
      },
      "dir": 1
    },
    {
      "id": "temporal_transition:temporal_process:belief_evolution→temporal_process:attention_and_reflection",
      "t": "temporal_transition",
      "s": "temporal_process:belief_evolution",
      "d": "temporal_process:attention_and_reflection",
      "w": 1,
      "style": {
        "stroke": "#B0B0B0",
        "sw": 1,
        "op": 0.4
      },
      "dir": 1
    },
    {
      "id": "temporal_transition:temporal_process:attention_and_reflection→temporal_process:time_perception",
      "t": "temporal_transition",
      "s": "temporal_process:attention_and_reflection",
      "d": "temporal_process:time_perception",
      "w": 1,
      "style": {
        "stroke": "#B0B0B0",
        "sw": 1,
        "op": 0.4
      },
      "dir": 1
    }
  ]
}